llmsec/__init__.py
llmsec/check_prompt.py
llmsec/check_prompt_result.py
llmsec/cli.py
llmsec-0.1.4.dist-info/LICENSE
llmsec-0.1.4.dist-info/METADATA
llmsec-0.1.4.dist-info/WHEEL
llmsec-0.1.4.dist-info/entry_points.txt
llmsec-0.1.4.dist-info/top_level.txt
llmsec-0.1.4.dist-info/RECORD
