Metadata-Version: 2.1
Name: llmsec
Version: 0.1.4
Summary: A Python library for LLM security
Author-email: Greg Retkowski <greg@rage.net>
Project-URL: Homepage, https://github.com/gregretkowski/llmsec
Classifier: Development Status :: 3 - Alpha
Classifier: Intended Audience :: Developers
Classifier: License :: OSI Approved :: MIT License
Classifier: Programming Language :: Python :: 3
Classifier: Programming Language :: Python :: 3.6
Classifier: Programming Language :: Python :: 3.7
Classifier: Programming Language :: Python :: 3.8
Classifier: Programming Language :: Python :: 3.9
License-File: LICENSE
Requires-Dist: litellm
Requires-Dist: python-dotenv
Requires-Dist: jinja2
Provides-Extra: dev
Requires-Dist: pylint; extra == "dev"
Requires-Dist: pytest; extra == "dev"
Requires-Dist: httpretty; extra == "dev"
